{"items":[{"tags":["perl"],"owner":{"reputation":41,"user_id":11690214,"user_type":"registered","profile_image":"https://www.gravatar.com/avatar/db211c870921bd0248928a0dfffe3e36?s=128&d=identicon&r=PG&f=1","display_name":"allmail","link":"https://stackoverflow.com/users/11690214/allmail"},"is_answered":true,"view_count":71,"answer_count":1,"score":5,"last_activity_date":1569525100,"creation_date":1568778923,"last_edit_date":1569267701,"question_id":57984872,"link":"https://stackoverflow.com/questions/57984872/perl-trying-to-understand-regex-debug-output","title":"Perl trying to understand regex debug output"},{"tags":["perl","grep"],"owner":{"reputation":121,"user_id":7484043,"user_type":"registered","profile_image":"https://www.gravatar.com/avatar/c553310d1ad27e031be3aefb8127db4f?s=128&d=identicon&r=PG&f=1","display_name":"sfr","link":"https://stackoverflow.com/users/7484043/sfr"},"is_answered":true,"view_count":35,"answer_count":2,"score":0,"last_activity_date":1569521591,"creation_date":1569454844,"last_edit_date":1569455762,"question_id":58107808,"link":"https://stackoverflow.com/questions/58107808/perl-system-grep-and-paste","title":"Perl System Grep and Paste"},{"tags":["mongodb","perl","asynchronous","insert","database-performance"],"owner":{"reputation":23,"user_id":9528148,"user_type":"registered","profile_image":"https://www.gravatar.com/avatar/094b40ec470688fc4d2f152ffbbd7251?s=128&d=identicon&r=PG&f=1","display_name":"Yuval","link":"https://stackoverflow.com/users/9528148/yuval"},"is_answered":false,"view_count":13,"answer_count":0,"score":0,"last_activity_date":1569520885,"creation_date":1569520885,"question_id":58122375,"link":"https://stackoverflow.com/questions/58122375/how-to-flush-asynchronously-to-mongodb-using-perl","title":"How to flush asynchronously to mongodb using Perl"},{"tags":["perl","templates","expression","freemarker"],"owner":{"reputation":1,"user_id":9602275,"user_type":"registered","profile_image":"https://www.gravatar.com/avatar/9a2a85504f21fdaa2365b74a6adf3cb8?s=128&d=identicon&r=PG&f=1","display_name":"goutham","link":"https://stackoverflow.com/users/9602275/goutham"},"is_answered":true,"view_count":36,"answer_count":2,"score":0,"last_activity_date":1569515984,"creation_date":1569396160,"question_id":58093157,"link":"https://stackoverflow.com/questions/58093157/apache-freemarker-template-module-for-perl","title":"Apache Freemarker Template module for perl"},{"tags":["perl"],"owner":{"reputation":1,"user_id":5080088,"user_type":"registered","profile_image":"https://lh6.googleusercontent.com/-enHC44r4RSw/AAAAAAAAAAI/AAAAAAAAAAA/yR1NkzfAXgM/photo.jpg?sz=128","display_name":"Pankaj Singh","link":"https://stackoverflow.com/users/5080088/pankaj-singh"},"is_answered":true,"view_count":26,"answer_count":1,"score":-1,"last_activity_date":1569513112,"creation_date":1569512380,"last_edit_date":1569512966,"question_id":58120347,"link":"https://stackoverflow.com/questions/58120347/mode-function-in-perl","title":"Mode function in Perl"},{"tags":["bash","perl","awk","sed"],"owner":{"reputation":1695,"user_id":987074,"user_type":"registered","accept_rate":77,"profile_image":"https://i.stack.imgur.com/rWIWG.jpg?s=128&g=1","display_name":"bdx","link":"https://stackoverflow.com/users/987074/bdx"},"is_answered":true,"view_count":59,"answer_count":4,"score":2,"last_activity_date":1569509731,"creation_date":1569465018,"question_id":58108791,"link":"https://stackoverflow.com/questions/58108791/multiline-perl-regex-replace-on-large-file-without-slurp","title":"Multiline perl regex replace on large file without slurp"},{"tags":["perl","centos","freeradius"],"owner":{"reputation":8,"user_id":12121412,"user_type":"registered","profile_image":"https://lh4.googleusercontent.com/-v83ATnbd3wA/AAAAAAAAAAI/AAAAAAAAAHo/fb9UOk11XMM/photo.jpg?sz=128","display_name":"Sama","link":"https://stackoverflow.com/users/12121412/sama"},"is_answered":true,"view_count":24,"accepted_answer_id":58119543,"answer_count":1,"score":1,"last_activity_date":1569509709,"creation_date":1569446524,"question_id":58106687,"link":"https://stackoverflow.com/questions/58106687/freeradius-perl-module-unknown-or-invalid-value-perl-for-attribute-auth-type","title":"FreeRADIUS Perl Module &quot;Unknown or invalid value &quot;perl&quot; for attribute Auth-Type&quot;"},{"tags":["perl","parsing","hash","subroutine"],"owner":{"reputation":42,"user_id":8826834,"user_type":"registered","profile_image":"https://i.stack.imgur.com/7TkaH.jpg?s=128&g=1","display_name":"Aletia","link":"https://stackoverflow.com/users/8826834/aletia"},"is_answered":true,"view_count":29,"answer_count":2,"score":1,"last_activity_date":1569508223,"creation_date":1569501081,"question_id":58116869,"link":"https://stackoverflow.com/questions/58116869/problems-with-output-order-after-returning-multiple-values-through-a-subroutine","title":"Problems with output order after returning multiple values through a subroutine in Perl"},{"tags":["perl","getopt-long"],"owner":{"reputation":1592,"user_id":3973175,"user_type":"registered","accept_rate":52,"profile_image":"https://www.gravatar.com/avatar/9c15391d610e59c350912be638b14074?s=128&d=identicon&r=PG","display_name":"con","link":"https://stackoverflow.com/users/3973175/con"},"is_answered":true,"view_count":20,"accepted_answer_id":58119019,"answer_count":1,"score":0,"last_activity_date":1569508030,"creation_date":1569507576,"last_edit_date":1569507989,"question_id":58118876,"link":"https://stackoverflow.com/questions/58118876/passing-arrays-to-getopt-in-perl","title":"Passing arrays to getopt in Perl"},{"tags":["perl","ldap","netldap"],"owner":{"reputation":334,"user_id":4279387,"user_type":"registered","accept_rate":69,"profile_image":"https://i.stack.imgur.com/yEPjV.png?s=128&g=1","display_name":"olivierg","link":"https://stackoverflow.com/users/4279387/olivierg"},"is_answered":false,"view_count":22,"answer_count":1,"score":0,"last_activity_date":1569501837,"creation_date":1569496403,"last_edit_date":1569496710,"question_id":58115567,"link":"https://stackoverflow.com/questions/58115567/use-file-for-filter-in-perl-netldap","title":"use file for filter in Perl Net::LDAP"},{"tags":["regex","perl"],"owner":{"reputation":210,"user_id":3337196,"user_type":"registered","accept_rate":75,"profile_image":"https://www.gravatar.com/avatar/d9559adf3cec6806c417d5aae1c7a85b?s=128&d=identicon&r=PG&f=1","display_name":"bilbo_pingouin","link":"https://stackoverflow.com/users/3337196/bilbo-pingouin"},"is_answered":true,"view_count":36,"accepted_answer_id":58113153,"answer_count":2,"score":1,"last_activity_date":1569491635,"creation_date":1569487476,"question_id":58112890,"link":"https://stackoverflow.com/questions/58112890/perl-iterate-over-the-number-of-regexp-matches","title":"Perl iterate over the number of regexp matches"},{"tags":["perl","ksh"],"owner":{"reputation":1,"user_id":12120069,"user_type":"registered","profile_image":"https://www.gravatar.com/avatar/002731692d019f09b6c306a9b71f4171?s=128&d=identicon&r=PG&f=1","display_name":"spudnik267","link":"https://stackoverflow.com/users/12120069/spudnik267"},"is_answered":false,"view_count":21,"answer_count":0,"score":0,"last_activity_date":1569488383,"creation_date":1569488383,"question_id":58113141,"link":"https://stackoverflow.com/questions/58113141/perl-script-prompts-for-password-but-does-not-accept-input-from-josh","title":"Perl script prompts for password but does not accept input from josh"},{"tags":["perl","cpan","dmake"],"owner":{"reputation":1,"user_id":12120845,"user_type":"registered","profile_image":"https://www.gravatar.com/avatar/d793cbe76d67ea210ff75ca058e0afb6?s=128&d=identicon&r=PG&f=1","display_name":"mwk","link":"https://stackoverflow.com/users/12120845/mwk"},"is_answered":false,"view_count":20,"answer_count":1,"score":0,"last_activity_date":1569482035,"creation_date":1569434857,"last_edit_date":1569482035,"question_id":58104250,"link":"https://stackoverflow.com/questions/58104250/dmake-not-found-when-installing-perl-module-using-cpan","title":"dmake not found when installing Perl module using CPAN"},{"tags":["perl"],"owner":{"reputation":58,"user_id":4448636,"user_type":"registered","accept_rate":25,"profile_image":"https://lh4.googleusercontent.com/-nFGT_d0g44k/AAAAAAAAAAI/AAAAAAAAAOU/1tWa-DCDtTE/photo.jpg?sz=128","display_name":"Rajar R","link":"https://stackoverflow.com/users/4448636/rajar-r"},"is_answered":true,"view_count":61,"answer_count":1,"score":1,"last_activity_date":1569480151,"creation_date":1569043150,"last_edit_date":1569043663,"question_id":58037486,"link":"https://stackoverflow.com/questions/58037486/find-file-in-perl-skip-permission-denied","title":"Find file in Perl —&#160;skip permission denied"},{"tags":["sql","sql-server","perl"],"owner":{"reputation":1377,"user_id":302249,"user_type":"registered","accept_rate":90,"profile_image":"https://www.gravatar.com/avatar/38c467a8b11ef0dde2bc97919502a047?s=128&d=identicon&r=PG","display_name":"Dan Walmsley","link":"https://stackoverflow.com/users/302249/dan-walmsley"},"is_answered":true,"view_count":35189,"accepted_answer_id":24029592,"answer_count":3,"score":12,"last_activity_date":1569470093,"creation_date":1401858877,"last_edit_date":1505228667,"question_id":24029518,"link":"https://stackoverflow.com/questions/24029518/insert-failed-because-the-following-set-options-have-incorrect-setting-only-in-p","title":"INSERT failed because the following SET options have incorrect setting only in Perl Sybase"},{"tags":["php","perl","curl"],"owner":{"reputation":49,"user_id":6175605,"user_type":"registered","accept_rate":58,"profile_image":"https://www.gravatar.com/avatar/f98957ca114e2ca1b3e06df1b7ac725f?s=128&d=identicon&r=PG&f=1","display_name":"icedoge","link":"https://stackoverflow.com/users/6175605/icedoge"},"is_answered":false,"view_count":33,"answer_count":0,"score":1,"last_activity_date":1569462764,"creation_date":1569461488,"last_edit_date":1569462764,"question_id":58108405,"link":"https://stackoverflow.com/questions/58108405/how-to-get-the-response-of-perl-post-from-curl-php","title":"How to get the response of Perl Post from Curl PHP"},{"tags":["python","perl"],"owner":{"reputation":20,"user_id":7869509,"user_type":"registered","profile_image":"https://www.gravatar.com/avatar/aa0f53445d9653733cf0bd641c7e03e5?s=128&d=identicon&r=PG&f=1","display_name":"Taliman","link":"https://stackoverflow.com/users/7869509/taliman"},"is_answered":false,"view_count":31,"closed_date":1569482576,"answer_count":0,"score":-1,"last_activity_date":1569458337,"creation_date":1569458337,"question_id":58108130,"link":"https://stackoverflow.com/questions/58108130/get-input-in-python-and-use-this-input-to-run-a-program-in-perl-and-then-give-ou","closed_reason":"too broad","title":"Get input in Python and use this input to run a program in Perl and then give output in Python"},{"tags":["python","regex","python-3.x"],"owner":{"reputation":111,"user_id":4460287,"user_type":"registered","accept_rate":48,"profile_image":"https://lh5.googleusercontent.com/-Mrh4dvnXd5c/AAAAAAAAAAI/AAAAAAAAAmY/6VfjyktC1J0/photo.jpg?sz=128","display_name":"Adhish Thite","link":"https://stackoverflow.com/users/4460287/adhish-thite"},"is_answered":false,"view_count":12,"closed_date":1569449200,"answer_count":0,"score":1,"last_activity_date":1569448949,"creation_date":1569448949,"question_id":58107115,"link":"https://stackoverflow.com/questions/58107115/appropriate-regex-format-for-python-perl-python-mismatch","closed_reason":"duplicate","title":"Appropriate Regex format for Python (Perl-Python Mismatch)"},{"tags":["perl","ubuntu","awk","sed"],"owner":{"reputation":2172,"user_id":189035,"user_type":"registered","accept_rate":98,"profile_image":"https://www.gravatar.com/avatar/39c115a166788050ce9f1d1f5eacdd96?s=128&d=identicon&r=PG","display_name":"user189035","link":"https://stackoverflow.com/users/189035/user189035"},"is_answered":true,"view_count":139,"accepted_answer_id":58089226,"answer_count":5,"score":3,"last_activity_date":1569440462,"creation_date":1569354757,"last_edit_date":1569440462,"question_id":58087298,"link":"https://stackoverflow.com/questions/58087298/sed-awk-perl-remove-the-first-two-lines-of-a-3-line-pattern","title":"sed/awk/perl remove the first two lines of a 3 line pattern"},{"tags":["perl"],"owner":{"reputation":1883,"user_id":251947,"user_type":"registered","accept_rate":67,"profile_image":"https://www.gravatar.com/avatar/80f18fe71d6fc0940ab8b7a036dd056e?s=128&d=identicon&r=PG","display_name":"Chris Koknat","link":"https://stackoverflow.com/users/251947/chris-koknat"},"is_answered":true,"view_count":7653,"accepted_answer_id":33442443,"answer_count":6,"score":4,"last_activity_date":1569437824,"creation_date":1446228117,"last_edit_date":1446228718,"question_id":33442240,"link":"https://stackoverflow.com/questions/33442240/perl-printf-to-use-commas-as-thousands-separator","title":"Perl printf to use commas as thousands-separator"},{"tags":["multithreading","perl","concurrency","directory","fork"],"owner":{"reputation":48,"user_id":5646911,"user_type":"registered","accept_rate":75,"profile_image":"https://www.gravatar.com/avatar/1053ff606f022044eadf048aa6a0c5ae?s=128&d=identicon&r=PG&f=1","display_name":"diborbi","link":"https://stackoverflow.com/users/5646911/diborbi"},"is_answered":true,"view_count":56,"answer_count":2,"score":0,"last_activity_date":1569429703,"creation_date":1538498342,"last_edit_date":1569429703,"question_id":52612742,"link":"https://stackoverflow.com/questions/52612742/perl-run-the-same-script-for-different-directories-at-the-same-time","title":"Perl run the same script for different directories at the same time"},{"tags":["regex","bash","shell","perl","command-line"],"owner":{"reputation":23,"user_id":10822962,"user_type":"registered","profile_image":"https://www.gravatar.com/avatar/41bbe5dda6d8fc828895f214bcd58d34?s=128&d=identicon&r=PG&f=1","display_name":"garys","link":"https://stackoverflow.com/users/10822962/garys"},"is_answered":true,"view_count":63,"accepted_answer_id":58099790,"answer_count":4,"score":3,"last_activity_date":1569418859,"creation_date":1569411620,"question_id":58097543,"link":"https://stackoverflow.com/questions/58097543/using-bash-variable-names-as-match-replacement-in-perl-regex-substitution-comman","title":"Using bash variable names as match replacement in perl regex substitution command line"},{"tags":["oracle","perl","dbd"],"owner":{"reputation":8,"user_id":8786691,"user_type":"registered","profile_image":"https://lh4.googleusercontent.com/-tCBlRcM0wNU/AAAAAAAAAAI/AAAAAAAAAjw/pkLKoISFeUw/photo.jpg?sz=128","display_name":"Kevin Murray","link":"https://stackoverflow.com/users/8786691/kevin-murray"},"is_answered":true,"view_count":53,"accepted_answer_id":58088703,"answer_count":1,"score":0,"last_activity_date":1569363806,"creation_date":1569360822,"question_id":58088422,"link":"https://stackoverflow.com/questions/58088422/perl-using-with-clause-in-database-prepare","title":"PERL using WITH clause in Database prepare"},{"tags":["arrays","perl","unique"],"owner":{"reputation":38,"user_id":2320229,"user_type":"registered","accept_rate":50,"profile_image":"https://www.gravatar.com/avatar/ff92a085b5efb2f06dec4321450c722c?s=128&d=identicon&r=PG","display_name":"user2320229","link":"https://stackoverflow.com/users/2320229/user2320229"},"is_answered":true,"view_count":1835,"accepted_answer_id":16217977,"answer_count":2,"score":1,"last_activity_date":1569362590,"creation_date":1366900611,"last_edit_date":1569362590,"question_id":16217677,"link":"https://stackoverflow.com/questions/16217677/finding-unique-values-in-two-arrays-perl","title":"Finding unique Values in two arrays - Perl"},{"tags":["perl","debugging","cpan","arrow-keys","perl5.12"],"owner":{"reputation":118,"user_id":1747399,"user_type":"registered","accept_rate":29,"profile_image":"https://www.gravatar.com/avatar/8193237e6de1d5c5ed7198c30a03b9ac?s=128&d=identicon&r=PG","display_name":"agaved","link":"https://stackoverflow.com/users/1747399/agaved"},"is_answered":true,"view_count":4468,"accepted_answer_id":13783342,"answer_count":7,"score":12,"last_activity_date":1569357875,"creation_date":1355011987,"last_edit_date":1468861507,"question_id":13783334,"link":"https://stackoverflow.com/questions/13783334/arrow-up-and-down-does-not-work-any-more-in-perl-debugger-and-cpan-client","title":"Arrow up and down does not work any more in Perl debugger and CPAN client"},{"tags":["regex","awk","sed","command-line"],"owner":{"reputation":48,"user_id":2504130,"user_type":"registered","profile_image":"https://graph.facebook.com/1397986023/picture?type=large","display_name":"16851556","link":"https://stackoverflow.com/users/2504130/16851556"},"is_answered":true,"view_count":38,"accepted_answer_id":58084444,"answer_count":1,"score":0,"last_activity_date":1569352238,"creation_date":1569341478,"last_edit_date":1569341633,"question_id":58084366,"link":"https://stackoverflow.com/questions/58084366/how-to-sed-or-perl-replace-text-with-dots-and-slashes-without-quotation-marks","title":"How to sed or perl replace text with dots and slashes without quotation marks?"},{"tags":["bash","perl","ini"],"owner":{"reputation":113,"user_id":270958,"user_type":"registered","accept_rate":0,"profile_image":"https://i.stack.imgur.com/ERBYI.jpg?s=128&g=1","display_name":"madsonic","link":"https://stackoverflow.com/users/270958/madsonic"},"is_answered":true,"view_count":79,"accepted_answer_id":58072050,"answer_count":3,"score":1,"last_activity_date":1569349597,"creation_date":1569275742,"last_edit_date":1569304526,"question_id":58070666,"link":"https://stackoverflow.com/questions/58070666/search-and-replace-items-within-an-ini-file-using-python2-7-perl-sed-within-a","title":"Search and replace items within an ini file, using python2.7, perl, sed within a bash one-liner"},{"tags":["perl","cpan","perlbrew"],"owner":{"reputation":1592,"user_id":3973175,"user_type":"registered","accept_rate":52,"profile_image":"https://www.gravatar.com/avatar/9c15391d610e59c350912be638b14074?s=128&d=identicon&r=PG","display_name":"con","link":"https://stackoverflow.com/users/3973175/con"},"is_answered":true,"view_count":30,"accepted_answer_id":58069753,"answer_count":1,"score":0,"last_activity_date":1569270388,"creation_date":1569267071,"last_edit_date":1569269521,"question_id":58069024,"link":"https://stackoverflow.com/questions/58069024/cannot-install-perl-package-vcf-via-cpan","title":"Cannot install perl package `Vcf` via CPAN"},{"tags":["perl","overloading"],"owner":{"reputation":777,"user_id":1961574,"user_type":"registered","accept_rate":64,"profile_image":"https://www.gravatar.com/avatar/184ac1de765a2428c4bbadfbf5beb517?s=128&d=identicon&r=PG&f=1","display_name":"bluppfisk","link":"https://stackoverflow.com/users/1961574/bluppfisk"},"is_answered":true,"view_count":68,"answer_count":2,"score":3,"last_activity_date":1569258208,"creation_date":1569251399,"question_id":58065366,"link":"https://stackoverflow.com/questions/58065366/overloading-a-perl-object-to-redirect-hash-access-to-custom-routine","title":"overloading a Perl object to redirect hash access to custom routine"},{"tags":["perl","command-line-arguments"],"owner":{"reputation":183,"user_id":9368481,"user_type":"registered","profile_image":"https://i.stack.imgur.com/gBMMe.png?s=128&g=1","display_name":"mHvNG","link":"https://stackoverflow.com/users/9368481/mhvng"},"is_answered":true,"view_count":83,"accepted_answer_id":58058341,"answer_count":1,"score":1,"last_activity_date":1569256963,"creation_date":1569222497,"question_id":58057274,"link":"https://stackoverflow.com/questions/58057274/perl-commandline-arguments","title":"Perl commandline arguments"}],"has_more":true,"quota_max":300,"quota_remaining":298}